[{"CODE": "CODE", "FLOW": "FLOW", "YEAR": "YEAR ", "QUANTITY_TON": "QUANTITY_TON"}, {"CODE": "FRA", "FLOW": "IMPORT", "YEAR": "2010", "QUANTITY_TON": "94035.3"}, {"CODE": "FRA", "FLOW": "IMPORT", "YEAR": "2011", "QUANTITY_TON": "88261.5"}, {"CODE": "FRA", "FLOW": "IMPORT", "YEAR": "2012", "QUANTITY_TON": "94499.6"}, {"CODE": "FRA", "FLOW": "IMPORT", "YEAR": "2013", "QUANTITY_TON": "100260.4"}, {"CODE": "FRA", "FLOW": "IMPORT", "YEAR": "2014", "QUANTITY_TON": "119722.6"}, {"CODE": "FRA", "FLOW": "IMPORT", "YEAR": "2015", "QUANTITY_TON": "116397.4"}, {"CODE": "FRA", "FLOW": "EXPORT", "YEAR": "2010", "QUANTITY_TON": "9526.4"}, {"CODE": "FRA", "FLOW": "EXPORT", "YEAR": "2011", "QUANTITY_TON": "12456.4"}, {"CODE": "FRA", "FLOW": "EXPORT", "YEAR": "2012", "QUANTITY_TON": "18072.3"}, {"CODE": "FRA", "FLOW": "EXPORT", "YEAR": "2013", "QUANTITY_TON": "14651.4"}, {"CODE": "FRA", "FLOW": "EXPORT", "YEAR": "2014", "QUANTITY_TON": "18660.2"}, {"CODE": "FRA", "FLOW": "EXPORT", "YEAR": "2015", "QUANTITY_TON": "19474.5"}, {"CODE": "NLD", "FLOW": "IMPORT", "YEAR": "2010", "QUANTITY_TON": "105978.90"}, {"CODE": "NLD", "FLOW": "IMPORT", "YEAR": "2011", "QUANTITY_TON": "104936.30"}, {"CODE": "NLD", "FLOW": "IMPORT", "YEAR": "2012", "QUANTITY_TON": "120322.00"}, {"CODE": "NLD", "FLOW": "IMPORT", "YEAR": "2013", "QUANTITY_TON": "143604.00"}, {"CODE": "NLD", "FLOW": "IMPORT", "YEAR": "2014", "QUANTITY_TON": "168760.90"}, {"CODE": "NLD", "FLOW": "IMPORT", "YEAR": "2015", "QUANTITY_TON": "187335.90"}, {"CODE": "NLD", "FLOW": "EXPORT", "YEAR": "2010", "QUANTITY_TON": "76030.30"}, {"CODE": "NLD", "FLOW": "EXPORT", "YEAR": "2011", "QUANTITY_TON": "82980.20"}, {"CODE": "NLD", "FLOW": "EXPORT", "YEAR": "2012", "QUANTITY_TON": "105055.10"}, {"CODE": "NLD", "FLOW": "EXPORT", "YEAR": "2013", "QUANTITY_TON": "120058.90"}, {"CODE": "NLD", "FLOW": "EXPORT", "YEAR": "2014", "QUANTITY_TON": "142984.40"}, {"CODE": "NLD", "FLOW": "EXPORT", "YEAR": "2015", "QUANTITY_TON": "151604.40"}, {"CODE": "DEU", "FLOW": "IMPORT", "YEAR": "2010", "QUANTITY_TON": "27914.50"}, {"CODE": "DEU", "FLOW": "IMPORT", "YEAR": "2011", "QUANTITY_TON": "29266.20"}, {"CODE": "DEU", "FLOW": "IMPORT", "YEAR": "2012", "QUANTITY_TON": "28998.40"}, {"CODE": "DEU", "FLOW": "IMPORT", "YEAR": "2013", "QUANTITY_TON": "31434.00"}, {"CODE": "DEU", "FLOW": "IMPORT", "YEAR": "2014", "QUANTITY_TON": "37714.00"}, {"CODE": "DEU", "FLOW": "IMPORT", "YEAR": "2015", "QUANTITY_TON": "48435.00"}, {"CODE": "DEU", "FLOW": "EXPORT", "YEAR": "2010", "QUANTITY_TON": "6081.00"}, {"CODE": "DEU", "FLOW": "EXPORT", "YEAR": "2011", "QUANTITY_TON": "5445.60"}, {"CODE": "DEU", "FLOW": "EXPORT", "YEAR": "2012", "QUANTITY_TON": "4584.60"}, {"CODE": "DEU", "FLOW": "EXPORT", "YEAR": "2013", "QUANTITY_TON": "5266.10"}, {"CODE": "DEU", "FLOW": "EXPORT", "YEAR": "2014", "QUANTITY_TON": "5730.60"}, {"CODE": "DEU", "FLOW": "EXPORT", "YEAR": "2015", "QUANTITY_TON": "10540.80"}, {"CODE": "ITA", "FLOW": "IMPORT", "YEAR": "2010", "QUANTITY_TON": "24691.20"}, {"CODE": "ITA", "FLOW": "IMPORT", "YEAR": "2011", "QUANTITY_TON": "14459.10"}, {"CODE": "ITA", "FLOW": "IMPORT", "YEAR": "2012", "QUANTITY_TON": "5149.10"}, {"CODE": "ITA", "FLOW": "IMPORT", "YEAR": "2013", "QUANTITY_TON": "6121.30"}, {"CODE": "ITA", "FLOW": "IMPORT", "YEAR": "2014", "QUANTITY_TON": "9109.10"}, {"CODE": "ITA", "FLOW": "IMPORT", "YEAR": "2015", "QUANTITY_TON": "10989.00"}, {"CODE": "ITA", "FLOW": "EXPORT", "YEAR": "2010", "QUANTITY_TON": "23868.80"}, {"CODE": "ITA", "FLOW": "EXPORT", "YEAR": "2011", "QUANTITY_TON": "9981.90"}, {"CODE": "ITA", "FLOW": "EXPORT", "YEAR": "2012", "QUANTITY_TON": "431.90"}, {"CODE": "ITA", "FLOW": "EXPORT", "YEAR": "2013", "QUANTITY_TON": "483.80"}, {"CODE": "ITA", "FLOW": "EXPORT", "YEAR": "2014", "QUANTITY_TON": "724.80"}, {"CODE": "ITA", "FLOW": "EXPORT", "YEAR": "2015", "QUANTITY_TON": "921.70"}, {"CODE": "GBR", "FLOW": "IMPORT", "YEAR": "2010", "QUANTITY_TON": "35240.90"}, {"CODE": "GBR", "FLOW": "IMPORT", "YEAR": "2011", "QUANTITY_TON": "34864.50"}, {"CODE": "GBR", "FLOW": "IMPORT", "YEAR": "2012", "QUANTITY_TON": "38095.70"}, {"CODE": "GBR", "FLOW": "IMPORT", "YEAR": "2013", "QUANTITY_TON": "41383.90"}, {"CODE": "GBR", "FLOW": "IMPORT", "YEAR": "2014", "QUANTITY_TON": "51552.70"}, {"CODE": "GBR", "FLOW": "IMPORT", "YEAR": "2015", "QUANTITY_TON": "73465.00"}, {"CODE": "GBR", "FLOW": "EXPORT", "YEAR": "2010", "QUANTITY_TON": "1180.10"}, {"CODE": "GBR", "FLOW": "EXPORT", "YEAR": "2011", "QUANTITY_TON": "1451.00"}, {"CODE": "GBR", "FLOW": "EXPORT", "YEAR": "2012", "QUANTITY_TON": "1830.20"}, {"CODE": "GBR", "FLOW": "EXPORT", "YEAR": "2013", "QUANTITY_TON": "1909.90"}, {"CODE": "GBR", "FLOW": "EXPORT", "YEAR": "2014", "QUANTITY_TON": "935.50"}, {"CODE": "GBR", "FLOW": "EXPORT", "YEAR": "2015", "QUANTITY_TON": "1688.40"}, {"CODE": "IRL", "FLOW": "IMPORT", "YEAR": "2010", "QUANTITY_TON": "2356.30"}, {"CODE": "IRL", "FLOW": "IMPORT", "YEAR": "2011", "QUANTITY_TON": "1905.40"}, {"CODE": "IRL", "FLOW": "IMPORT", "YEAR": "2012", "QUANTITY_TON": "2049.80"}, {"CODE": "IRL", "FLOW": "IMPORT", "YEAR": "2013", "QUANTITY_TON": "2311.70"}, {"CODE": "IRL", "FLOW": "IMPORT", "YEAR": "2014", "QUANTITY_TON": "2669.20"}, {"CODE": "IRL", "FLOW": "IMPORT", "YEAR": "2015", "QUANTITY_TON": "4351.30"}, {"CODE": "IRL", "FLOW": "EXPORT", "YEAR": "2010", "QUANTITY_TON": "9.60"}, {"CODE": "IRL", "FLOW": "EXPORT", "YEAR": "2011", "QUANTITY_TON": "6.20"}, {"CODE": "IRL", "FLOW": "EXPORT", "YEAR": "2012", "QUANTITY_TON": "60.40"}, {"CODE": "IRL", "FLOW": "EXPORT", "YEAR": "2013", "QUANTITY_TON": "16.10"}, {"CODE": "IRL", "FLOW": "EXPORT", "YEAR": "2014", "QUANTITY_TON": "9.20"}, {"CODE": "IRL", "FLOW": "EXPORT", "YEAR": "2015", "QUANTITY_TON": "8.40"}, {"CODE": "DNK", "FLOW": "IMPORT", "YEAR": "2010", "QUANTITY_TON": "10521.40"}, {"CODE": "DNK", "FLOW": "IMPORT", "YEAR": "2011", "QUANTITY_TON": "10307.40"}, {"CODE": "DNK", "FLOW": "IMPORT", "YEAR": "2012", "QUANTITY_TON": "11855.70"}, {"CODE": "DNK", "FLOW": "IMPORT", "YEAR": "2013", "QUANTITY_TON": "10105.20"}, {"CODE": "DNK", "FLOW": "IMPORT", "YEAR": "2014", "QUANTITY_TON": "10978.00"}, {"CODE": "DNK", "FLOW": "IMPORT", "YEAR": "2015", "QUANTITY_TON": "14190.20"}, {"CODE": "DNK", "FLOW": "EXPORT", "YEAR": "2010", "QUANTITY_TON": "442.70"}, {"CODE": "DNK", "FLOW": "EXPORT", "YEAR": "2011", "QUANTITY_TON": "577.30"}, {"CODE": "DNK", "FLOW": "EXPORT", "YEAR": "2012", "QUANTITY_TON": "265.10"}, {"CODE": "DNK", "FLOW": "EXPORT", "YEAR": "2013", "QUANTITY_TON": "346.00"}, {"CODE": "DNK", "FLOW": "EXPORT", "YEAR": "2014", "QUANTITY_TON": "260.60"}, {"CODE": "DNK", "FLOW": "EXPORT", "YEAR": "2015", "QUANTITY_TON": "363.30"}, {"CODE": "GRC", "FLOW": "IMPORT", "YEAR": "2010", "QUANTITY_TON": "721.00"}, {"CODE": "GRC", "FLOW": "IMPORT", "YEAR": "2011", "QUANTITY_TON": "1030.30"}, {"CODE": "GRC", "FLOW": "IMPORT", "YEAR": "2012", "QUANTITY_TON": "847.80"}, {"CODE": "GRC", "FLOW": "IMPORT", "YEAR": "2013", "QUANTITY_TON": "1165.00"}, {"CODE": "GRC", "FLOW": "IMPORT", "YEAR": "2014", "QUANTITY_TON": "1405.50"}, {"CODE": "GRC", "FLOW": "IMPORT", "YEAR": "2015", "QUANTITY_TON": "1617.70"}, {"CODE": "GRC", "FLOW": "EXPORT", "YEAR": "2010", "QUANTITY_TON": "861.60"}, {"CODE": "GRC", "FLOW": "EXPORT", "YEAR": "2011", "QUANTITY_TON": "441.60"}, {"CODE": "GRC", "FLOW": "EXPORT", "YEAR": "2012", "QUANTITY_TON": "682.10"}, {"CODE": "GRC", "FLOW": "EXPORT", "YEAR": "2013", "QUANTITY_TON": "521.90"}, {"CODE": "GRC", "FLOW": "EXPORT", "YEAR": "2014", "QUANTITY_TON": "781.20"}, {"CODE": "GRC", "FLOW": "EXPORT", "YEAR": "2015", "QUANTITY_TON": "892.00"}, {"CODE": "PRT", "FLOW": "IMPORT", "YEAR": "2010", "QUANTITY_TON": "720.60"}, {"CODE": "PRT", "FLOW": "IMPORT", "YEAR": "2011", "QUANTITY_TON": "498.00"}, {"CODE": "PRT", "FLOW": "IMPORT", "YEAR": "2012", "QUANTITY_TON": "658.70"}, {"CODE": "PRT", "FLOW": "IMPORT", "YEAR": "2013", "QUANTITY_TON": "1126.90"}, {"CODE": "PRT", "FLOW": "IMPORT", "YEAR": "2014", "QUANTITY_TON": "1131.20"}, {"CODE": "PRT", "FLOW": "IMPORT", "YEAR": "2015", "QUANTITY_TON": "1333.90"}, {"CODE": "PRT", "FLOW": "EXPORT", "YEAR": "2010", "QUANTITY_TON": "91.00"}, {"CODE": "PRT", "FLOW": "EXPORT", "YEAR": "2011", "QUANTITY_TON": "493.80"}, {"CODE": "PRT", "FLOW": "EXPORT", "YEAR": "2012", "QUANTITY_TON": "606.80"}, {"CODE": "PRT", "FLOW": "EXPORT", "YEAR": "2013", "QUANTITY_TON": "435.60"}, {"CODE": "PRT", "FLOW": "EXPORT", "YEAR": "2014", "QUANTITY_TON": "642.90"}, {"CODE": "PRT", "FLOW": "EXPORT", "YEAR": "2015", "QUANTITY_TON": "1737.70"}, {"CODE": "ESP", "FLOW": "IMPORT", "YEAR": "2010", "QUANTITY_TON": "32822.60"}, {"CODE": "ESP", "FLOW": "IMPORT", "YEAR": "2011", "QUANTITY_TON": "29848.00"}, {"CODE": "ESP", "FLOW": "IMPORT", "YEAR": "2012", "QUANTITY_TON": "34061.10"}, {"CODE": "ESP", "FLOW": "IMPORT", "YEAR": "2013", "QUANTITY_TON": "41049.70"}, {"CODE": "ESP", "FLOW": "IMPORT", "YEAR": "2014", "QUANTITY_TON": "52746.70"}, {"CODE": "ESP", "FLOW": "IMPORT", "YEAR": "2015", "QUANTITY_TON": "60988.90"}, {"CODE": "ESP", "FLOW": "EXPORT", "YEAR": "2010", "QUANTITY_TON": "54421.90"}, {"CODE": "ESP", "FLOW": "EXPORT", "YEAR": "2011", "QUANTITY_TON": "70887.80"}, {"CODE": "ESP", "FLOW": "EXPORT", "YEAR": "2012", "QUANTITY_TON": "65493.90"}, {"CODE": "ESP", "FLOW": "EXPORT", "YEAR": "2013", "QUANTITY_TON": "66116.00"}, {"CODE": "ESP", "FLOW": "EXPORT", "YEAR": "2014", "QUANTITY_TON": "75474.50"}, {"CODE": "ESP", "FLOW": "EXPORT", "YEAR": "2015", "QUANTITY_TON": "85737.10"}, {"CODE": "BEL", "FLOW": "IMPORT", "YEAR": "2010", "QUANTITY_TON": "5850.90"}, {"CODE": "BEL", "FLOW": "IMPORT", "YEAR": "2011", "QUANTITY_TON": "6004.40"}, {"CODE": "BEL", "FLOW": "IMPORT", "YEAR": "2012", "QUANTITY_TON": "12349.30"}, {"CODE": "BEL", "FLOW": "IMPORT", "YEAR": "2013", "QUANTITY_TON": "14370.20"}, {"CODE": "BEL", "FLOW": "IMPORT", "YEAR": "2014", "QUANTITY_TON": "17127.20"}, {"CODE": "BEL", "FLOW": "IMPORT", "YEAR": "2015", "QUANTITY_TON": "20378.40"}, {"CODE": "BEL", "FLOW": "EXPORT", "YEAR": "2010", "QUANTITY_TON": "2608.40"}, {"CODE": "BEL", "FLOW": "EXPORT", "YEAR": "2011", "QUANTITY_TON": "2057.10"}, {"CODE": "BEL", "FLOW": "EXPORT", "YEAR": "2012", "QUANTITY_TON": "6439.90"}, {"CODE": "BEL", "FLOW": "EXPORT", "YEAR": "2013", "QUANTITY_TON": "8650.00"}, {"CODE": "BEL", "FLOW": "EXPORT", "YEAR": "2014", "QUANTITY_TON": "11246.30"}, {"CODE": "BEL", "FLOW": "EXPORT", "YEAR": "2015", "QUANTITY_TON": "14057.50"}, {"CODE": "LUX", "FLOW": "IMPORT", "YEAR": "2010", "QUANTITY_TON": "257.50"}, {"CODE": "LUX", "FLOW": "IMPORT", "YEAR": "2011", "QUANTITY_TON": "262.20"}, {"CODE": "LUX", "FLOW": "IMPORT", "YEAR": "2012", "QUANTITY_TON": "209.70"}, {"CODE": "LUX", "FLOW": "IMPORT", "YEAR": "2013", "QUANTITY_TON": "237.00"}, {"CODE": "LUX", "FLOW": "IMPORT", "YEAR": "2014", "QUANTITY_TON": "366.70"}, {"CODE": "LUX", "FLOW": "IMPORT", "YEAR": "2015", "QUANTITY_TON": "358.60"}, {"CODE": "LUX", "FLOW": "EXPORT", "YEAR": "2010", "QUANTITY_TON": "25.40"}, {"CODE": "LUX", "FLOW": "EXPORT", "YEAR": "2011", "QUANTITY_TON": "29.30"}, {"CODE": "LUX", "FLOW": "EXPORT", "YEAR": "2012", "QUANTITY_TON": "19.80"}, {"CODE": "LUX", "FLOW": "EXPORT", "YEAR": "2013", "QUANTITY_TON": "16.30"}, {"CODE": "LUX", "FLOW": "EXPORT", "YEAR": "2014", "QUANTITY_TON": "22.30"}, {"CODE": "LUX", "FLOW": "EXPORT", "YEAR": "2015", "QUANTITY_TON": "17.30"}, {"CODE": "SWE", "FLOW": "IMPORT", "YEAR": "2010", "QUANTITY_TON": "14183.00"}, {"CODE": "SWE", "FLOW": "IMPORT", "YEAR": "2011", "QUANTITY_TON": "16563.30"}, {"CODE": "SWE", "FLOW": "IMPORT", "YEAR": "2012", "QUANTITY_TON": "18795.90"}, {"CODE": "SWE", "FLOW": "IMPORT", "YEAR": "2013", "QUANTITY_TON": "19655.60"}, {"CODE": "SWE", "FLOW": "IMPORT", "YEAR": "2014", "QUANTITY_TON": "19370.90"}, {"CODE": "SWE", "FLOW": "IMPORT", "YEAR": "2015", "QUANTITY_TON": "17878.50"}, {"CODE": "SWE", "FLOW": "EXPORT", "YEAR": "2010", "QUANTITY_TON": "785.00"}, {"CODE": "SWE", "FLOW": "EXPORT", "YEAR": "2011", "QUANTITY_TON": "216.30"}, {"CODE": "SWE", "FLOW": "EXPORT", "YEAR": "2012", "QUANTITY_TON": "15.10"}, {"CODE": "SWE", "FLOW": "EXPORT", "YEAR": "2013", "QUANTITY_TON": "41.30"}, {"CODE": "SWE", "FLOW": "EXPORT", "YEAR": "2014", "QUANTITY_TON": "31.60"}, {"CODE": "SWE", "FLOW": "EXPORT", "YEAR": "2015", "QUANTITY_TON": "79.70"}, {"CODE": "FIN", "FLOW": "IMPORT", "YEAR": "2010", "QUANTITY_TON": "1479.20"}, {"CODE": "FIN", "FLOW": "IMPORT", "YEAR": "2011", "QUANTITY_TON": "2073.20"}, {"CODE": "FIN", "FLOW": "IMPORT", "YEAR": "2012", "QUANTITY_TON": "2215.60"}, {"CODE": "FIN", "FLOW": "IMPORT", "YEAR": "2013", "QUANTITY_TON": "4435.10"}, {"CODE": "FIN", "FLOW": "IMPORT", "YEAR": "2014", "QUANTITY_TON": "6243.30"}, {"CODE": "FIN", "FLOW": "IMPORT", "YEAR": "2015", "QUANTITY_TON": "7491.80"}, {"CODE": "FIN", "FLOW": "EXPORT", "YEAR": "2010", "QUANTITY_TON": "0.10"}, {"CODE": "FIN", "FLOW": "EXPORT", "YEAR": "2011", "QUANTITY_TON": "0.10"}, {"CODE": "FIN", "FLOW": "EXPORT", "YEAR": "2012", "QUANTITY_TON": "0.00"}, {"CODE": "FIN", "FLOW": "EXPORT", "YEAR": "2013", "QUANTITY_TON": "2.50"}, {"CODE": "FIN", "FLOW": "EXPORT", "YEAR": "2014", "QUANTITY_TON": "14.30"}, {"CODE": "FIN", "FLOW": "EXPORT", "YEAR": "2015", "QUANTITY_TON": "49.70"}, {"CODE": "AUT", "FLOW": "IMPORT", "YEAR": "2010", "QUANTITY_TON": "3062.20"}, {"CODE": "AUT", "FLOW": "IMPORT", "YEAR": "2011", "QUANTITY_TON": "2995.10"}, {"CODE": "AUT", "FLOW": "IMPORT", "YEAR": "2012", "QUANTITY_TON": "2761.50"}, {"CODE": "AUT", "FLOW": "IMPORT", "YEAR": "2013", "QUANTITY_TON": "3420.10"}, {"CODE": "AUT", "FLOW": "IMPORT", "YEAR": "2014", "QUANTITY_TON": "4420.30"}, {"CODE": "AUT", "FLOW": "IMPORT", "YEAR": "2015", "QUANTITY_TON": "5810.20"}, {"CODE": "AUT", "FLOW": "EXPORT", "YEAR": "2010", "QUANTITY_TON": "370.10"}, {"CODE": "AUT", "FLOW": "EXPORT", "YEAR": "2011", "QUANTITY_TON": "332.30"}, {"CODE": "AUT", "FLOW": "EXPORT", "YEAR": "2012", "QUANTITY_TON": "592.20"}, {"CODE": "AUT", "FLOW": "EXPORT", "YEAR": "2013", "QUANTITY_TON": "558.00"}, {"CODE": "AUT", "FLOW": "EXPORT", "YEAR": "2014", "QUANTITY_TON": "681.90"}, {"CODE": "AUT", "FLOW": "EXPORT", "YEAR": "2015", "QUANTITY_TON": "839.30"}, {"CODE": "MLT", "FLOW": "IMPORT", "YEAR": "2010", "QUANTITY_TON": "85.30"}, {"CODE": "MLT", "FLOW": "IMPORT", "YEAR": "2011", "QUANTITY_TON": "75.50"}, {"CODE": "MLT", "FLOW": "IMPORT", "YEAR": "2012", "QUANTITY_TON": "86.40"}, {"CODE": "MLT", "FLOW": "IMPORT", "YEAR": "2013", "QUANTITY_TON": "105.70"}, {"CODE": "MLT", "FLOW": "IMPORT", "YEAR": "2014", "QUANTITY_TON": "178.50"}, {"CODE": "MLT", "FLOW": "IMPORT", "YEAR": "2015", "QUANTITY_TON": "311.30"}, {"CODE": "MLT", "FLOW": "EXPORT", "YEAR": "2010", "QUANTITY_TON": "0.00"}, {"CODE": "MLT", "FLOW": "EXPORT", "YEAR": "2011", "QUANTITY_TON": "0.00"}, {"CODE": "MLT", "FLOW": "EXPORT", "YEAR": "2012", "QUANTITY_TON": "0.00"}, {"CODE": "MLT", "FLOW": "EXPORT", "YEAR": "2013", "QUANTITY_TON": "0.00"}, {"CODE": "MLT", "FLOW": "EXPORT", "YEAR": "2014", "QUANTITY_TON": "0.00"}, {"CODE": "MLT", "FLOW": "EXPORT", "YEAR": "2015", "QUANTITY_TON": "0.00"}, {"CODE": "EST", "FLOW": "IMPORT", "YEAR": "2010", "QUANTITY_TON": "261.90"}, {"CODE": "EST", "FLOW": "IMPORT", "YEAR": "2011", "QUANTITY_TON": "265.90"}, {"CODE": "EST", "FLOW": "IMPORT", "YEAR": "2012", "QUANTITY_TON": "285.30"}, {"CODE": "EST", "FLOW": "IMPORT", "YEAR": "2013", "QUANTITY_TON": "565.90"}, {"CODE": "EST", "FLOW": "IMPORT", "YEAR": "2014", "QUANTITY_TON": "751.70"}, {"CODE": "EST", "FLOW": "IMPORT", "YEAR": "2015", "QUANTITY_TON": "1014.80"}, {"CODE": "EST", "FLOW": "EXPORT", "YEAR": "2010", "QUANTITY_TON": "0.30"}, {"CODE": "EST", "FLOW": "EXPORT", "YEAR": "2011", "QUANTITY_TON": "0.20"}, {"CODE": "EST", "FLOW": "EXPORT", "YEAR": "2012", "QUANTITY_TON": "3.40"}, {"CODE": "EST", "FLOW": "EXPORT", "YEAR": "2013", "QUANTITY_TON": "0.00"}, {"CODE": "EST", "FLOW": "EXPORT", "YEAR": "2014", "QUANTITY_TON": "0.10"}, {"CODE": "EST", "FLOW": "EXPORT", "YEAR": "2015", "QUANTITY_TON": "4.40"}, {"CODE": "LVA", "FLOW": "IMPORT", "YEAR": "2010", "QUANTITY_TON": "2126.40"}, {"CODE": "LVA", "FLOW": "IMPORT", "YEAR": "2011", "QUANTITY_TON": "2819.20"}, {"CODE": "LVA", "FLOW": "IMPORT", "YEAR": "2012", "QUANTITY_TON": "3064.30"}, {"CODE": "LVA", "FLOW": "IMPORT", "YEAR": "2013", "QUANTITY_TON": "3543.30"}, {"CODE": "LVA", "FLOW": "IMPORT", "YEAR": "2014", "QUANTITY_TON": "3250.80"}, {"CODE": "LVA", "FLOW": "IMPORT", "YEAR": "2015", "QUANTITY_TON": "2421.90"}, {"CODE": "LVA", "FLOW": "EXPORT", "YEAR": "2010", "QUANTITY_TON": "440.30"}, {"CODE": "LVA", "FLOW": "EXPORT", "YEAR": "2011", "QUANTITY_TON": "771.10"}, {"CODE": "LVA", "FLOW": "EXPORT", "YEAR": "2012", "QUANTITY_TON": "654.60"}, {"CODE": "LVA", "FLOW": "EXPORT", "YEAR": "2013", "QUANTITY_TON": "979.30"}, {"CODE": "LVA", "FLOW": "EXPORT", "YEAR": "2014", "QUANTITY_TON": "1055.80"}, {"CODE": "LVA", "FLOW": "EXPORT", "YEAR": "2015", "QUANTITY_TON": "824.30"}, {"CODE": "LTU", "FLOW": "IMPORT", "YEAR": "2010", "QUANTITY_TON": "3884.40"}, {"CODE": "LTU", "FLOW": "IMPORT", "YEAR": "2011", "QUANTITY_TON": "4613.30"}, {"CODE": "LTU", "FLOW": "IMPORT", "YEAR": "2012", "QUANTITY_TON": "5684.50"}, {"CODE": "LTU", "FLOW": "IMPORT", "YEAR": "2013", "QUANTITY_TON": "6502.60"}, {"CODE": "LTU", "FLOW": "IMPORT", "YEAR": "2014", "QUANTITY_TON": "6037.40"}, {"CODE": "LTU", "FLOW": "IMPORT", "YEAR": "2015", "QUANTITY_TON": "6396.60"}, {"CODE": "LTU", "FLOW": "EXPORT", "YEAR": "2010", "QUANTITY_TON": "3181.00"}, {"CODE": "LTU", "FLOW": "EXPORT", "YEAR": "2011", "QUANTITY_TON": "3857.80"}, {"CODE": "LTU", "FLOW": "EXPORT", "YEAR": "2012", "QUANTITY_TON": "4593.90"}, {"CODE": "LTU", "FLOW": "EXPORT", "YEAR": "2013", "QUANTITY_TON": "5210.30"}, {"CODE": "LTU", "FLOW": "EXPORT", "YEAR": "2014", "QUANTITY_TON": "4047.10"}, {"CODE": "LTU", "FLOW": "EXPORT", "YEAR": "2015", "QUANTITY_TON": "1440.90"}, {"CODE": "POL", "FLOW": "IMPORT", "YEAR": "2010", "QUANTITY_TON": "2860.80"}, {"CODE": "POL", "FLOW": "IMPORT", "YEAR": "2011", "QUANTITY_TON": "2874.50"}, {"CODE": "POL", "FLOW": "IMPORT", "YEAR": "2012", "QUANTITY_TON": "3047.70"}, {"CODE": "POL", "FLOW": "IMPORT", "YEAR": "2013", "QUANTITY_TON": "4752.30"}, {"CODE": "POL", "FLOW": "IMPORT", "YEAR": "2014", "QUANTITY_TON": "7221.30"}, {"CODE": "POL", "FLOW": "IMPORT", "YEAR": "2015", "QUANTITY_TON": "9269.90"}, {"CODE": "POL", "FLOW": "EXPORT", "YEAR": "2010", "QUANTITY_TON": "273.30"}, {"CODE": "POL", "FLOW": "EXPORT", "YEAR": "2011", "QUANTITY_TON": "521.40"}, {"CODE": "POL", "FLOW": "EXPORT", "YEAR": "2012", "QUANTITY_TON": "678.50"}, {"CODE": "POL", "FLOW": "EXPORT", "YEAR": "2013", "QUANTITY_TON": "936.70"}, {"CODE": "POL", "FLOW": "EXPORT", "YEAR": "2014", "QUANTITY_TON": "1006.40"}, {"CODE": "POL", "FLOW": "EXPORT", "YEAR": "2015", "QUANTITY_TON": "865.40"}, {"CODE": "CZE", "FLOW": "IMPORT", "YEAR": "2010", "QUANTITY_TON": "707.80"}, {"CODE": "CZE", "FLOW": "IMPORT", "YEAR": "2011", "QUANTITY_TON": "611.60"}, {"CODE": "CZE", "FLOW": "IMPORT", "YEAR": "2012", "QUANTITY_TON": "839.40"}, {"CODE": "CZE", "FLOW": "IMPORT", "YEAR": "2013", "QUANTITY_TON": "1412.80"}, {"CODE": "CZE", "FLOW": "IMPORT", "YEAR": "2014", "QUANTITY_TON": "2063.10"}, {"CODE": "CZE", "FLOW": "IMPORT", "YEAR": "2015", "QUANTITY_TON": "2464.90"}, {"CODE": "CZE", "FLOW": "EXPORT", "YEAR": "2010", "QUANTITY_TON": "125.00"}, {"CODE": "CZE", "FLOW": "EXPORT", "YEAR": "2011", "QUANTITY_TON": "98.30"}, {"CODE": "CZE", "FLOW": "EXPORT", "YEAR": "2012", "QUANTITY_TON": "45.70"}, {"CODE": "CZE", "FLOW": "EXPORT", "YEAR": "2013", "QUANTITY_TON": "188.10"}, {"CODE": "CZE", "FLOW": "EXPORT", "YEAR": "2014", "QUANTITY_TON": "473.70"}, {"CODE": "CZE", "FLOW": "EXPORT", "YEAR": "2015", "QUANTITY_TON": "486.10"}, {"CODE": "SVK", "FLOW": "IMPORT", "YEAR": "2010", "QUANTITY_TON": "341.40"}, {"CODE": "SVK", "FLOW": "IMPORT", "YEAR": "2011", "QUANTITY_TON": "438.90"}, {"CODE": "SVK", "FLOW": "IMPORT", "YEAR": "2012", "QUANTITY_TON": "548.40"}, {"CODE": "SVK", "FLOW": "IMPORT", "YEAR": "2013", "QUANTITY_TON": "565.00"}, {"CODE": "SVK", "FLOW": "IMPORT", "YEAR": "2014", "QUANTITY_TON": "942.00"}, {"CODE": "SVK", "FLOW": "IMPORT", "YEAR": "2015", "QUANTITY_TON": "941.50"}, {"CODE": "SVK", "FLOW": "EXPORT", "YEAR": "2010", "QUANTITY_TON": "0.20"}, {"CODE": "SVK", "FLOW": "EXPORT", "YEAR": "2011", "QUANTITY_TON": "0.00"}, {"CODE": "SVK", "FLOW": "EXPORT", "YEAR": "2012", "QUANTITY_TON": "0.00"}, {"CODE": "SVK", "FLOW": "EXPORT", "YEAR": "2013", "QUANTITY_TON": "0.90"}, {"CODE": "SVK", "FLOW": "EXPORT", "YEAR": "2014", "QUANTITY_TON": "4.20"}, {"CODE": "SVK", "FLOW": "EXPORT", "YEAR": "2015", "QUANTITY_TON": "3.00"}, {"CODE": "HUN", "FLOW": "IMPORT", "YEAR": "2010", "QUANTITY_TON": "419.50"}, {"CODE": "HUN", "FLOW": "IMPORT", "YEAR": "2011", "QUANTITY_TON": "434.40"}, {"CODE": "HUN", "FLOW": "IMPORT", "YEAR": "2012", "QUANTITY_TON": "741.20"}, {"CODE": "HUN", "FLOW": "IMPORT", "YEAR": "2013", "QUANTITY_TON": "847.80"}, {"CODE": "HUN", "FLOW": "IMPORT", "YEAR": "2014", "QUANTITY_TON": "1966.80"}, {"CODE": "HUN", "FLOW": "IMPORT", "YEAR": "2015", "QUANTITY_TON": "1762.90"}, {"CODE": "HUN", "FLOW": "EXPORT", "YEAR": "2010", "QUANTITY_TON": "0.00"}, {"CODE": "HUN", "FLOW": "EXPORT", "YEAR": "2011", "QUANTITY_TON": "46.10"}, {"CODE": "HUN", "FLOW": "EXPORT", "YEAR": "2012", "QUANTITY_TON": "91.30"}, {"CODE": "HUN", "FLOW": "EXPORT", "YEAR": "2013", "QUANTITY_TON": "44.90"}, {"CODE": "HUN", "FLOW": "EXPORT", "YEAR": "2014", "QUANTITY_TON": "228.90"}, {"CODE": "HUN", "FLOW": "EXPORT", "YEAR": "2015", "QUANTITY_TON": "194.00"}, {"CODE": "ROU", "FLOW": "IMPORT", "YEAR": "2010", "QUANTITY_TON": "499.90"}, {"CODE": "ROU", "FLOW": "IMPORT", "YEAR": "2011", "QUANTITY_TON": "449.70"}, {"CODE": "ROU", "FLOW": "IMPORT", "YEAR": "2012", "QUANTITY_TON": "858.30"}, {"CODE": "ROU", "FLOW": "IMPORT", "YEAR": "2013", "QUANTITY_TON": "1395.80"}, {"CODE": "ROU", "FLOW": "IMPORT", "YEAR": "2014", "QUANTITY_TON": "2461.80"}, {"CODE": "ROU", "FLOW": "IMPORT", "YEAR": "2015", "QUANTITY_TON": "3012.50"}, {"CODE": "ROU", "FLOW": "EXPORT", "YEAR": "2010", "QUANTITY_TON": "16.00"}, {"CODE": "ROU", "FLOW": "EXPORT", "YEAR": "2011", "QUANTITY_TON": "130.90"}, {"CODE": "ROU", "FLOW": "EXPORT", "YEAR": "2012", "QUANTITY_TON": "155.40"}, {"CODE": "ROU", "FLOW": "EXPORT", "YEAR": "2013", "QUANTITY_TON": "55.70"}, {"CODE": "ROU", "FLOW": "EXPORT", "YEAR": "2014", "QUANTITY_TON": "51.70"}, {"CODE": "ROU", "FLOW": "EXPORT", "YEAR": "2015", "QUANTITY_TON": "16.90"}, {"CODE": "BGR", "FLOW": "IMPORT", "YEAR": "2010", "QUANTITY_TON": "151.10"}, {"CODE": "BGR", "FLOW": "IMPORT", "YEAR": "2011", "QUANTITY_TON": "289.70"}, {"CODE": "BGR", "FLOW": "IMPORT", "YEAR": "2012", "QUANTITY_TON": "330.10"}, {"CODE": "BGR", "FLOW": "IMPORT", "YEAR": "2013", "QUANTITY_TON": "371.80"}, {"CODE": "BGR", "FLOW": "IMPORT", "YEAR": "2014", "QUANTITY_TON": "713.10"}, {"CODE": "BGR", "FLOW": "IMPORT", "YEAR": "2015", "QUANTITY_TON": "851.00"}, {"CODE": "BGR", "FLOW": "EXPORT", "YEAR": "2010", "QUANTITY_TON": "0.50"}, {"CODE": "BGR", "FLOW": "EXPORT", "YEAR": "2011", "QUANTITY_TON": "0.00"}, {"CODE": "BGR", "FLOW": "EXPORT", "YEAR": "2012", "QUANTITY_TON": "2.50"}, {"CODE": "BGR", "FLOW": "EXPORT", "YEAR": "2013", "QUANTITY_TON": "0.10"}, {"CODE": "BGR", "FLOW": "EXPORT", "YEAR": "2014", "QUANTITY_TON": "4.50"}, {"CODE": "BGR", "FLOW": "EXPORT", "YEAR": "2015", "QUANTITY_TON": "25.90"}, {"CODE": "SVN", "FLOW": "IMPORT", "YEAR": "2010", "QUANTITY_TON": "2491.40"}, {"CODE": "SVN", "FLOW": "IMPORT", "YEAR": "2011", "QUANTITY_TON": "2398.20"}, {"CODE": "SVN", "FLOW": "IMPORT", "YEAR": "2012", "QUANTITY_TON": "1562.50"}, {"CODE": "SVN", "FLOW": "IMPORT", "YEAR": "2013", "QUANTITY_TON": "1662.00"}, {"CODE": "SVN", "FLOW": "IMPORT", "YEAR": "2014", "QUANTITY_TON": "1798.40"}, {"CODE": "SVN", "FLOW": "IMPORT", "YEAR": "2015", "QUANTITY_TON": "2479.70"}, {"CODE": "SVN", "FLOW": "EXPORT", "YEAR": "2010", "QUANTITY_TON": "2242.30"}, {"CODE": "SVN", "FLOW": "EXPORT", "YEAR": "2011", "QUANTITY_TON": "2243.10"}, {"CODE": "SVN", "FLOW": "EXPORT", "YEAR": "2012", "QUANTITY_TON": "985.40"}, {"CODE": "SVN", "FLOW": "EXPORT", "YEAR": "2013", "QUANTITY_TON": "628.40"}, {"CODE": "SVN", "FLOW": "EXPORT", "YEAR": "2014", "QUANTITY_TON": "1247.10"}, {"CODE": "SVN", "FLOW": "EXPORT", "YEAR": "2015", "QUANTITY_TON": "1953.10"}, {"CODE": "HRV", "FLOW": "IMPORT", "YEAR": "2010", "QUANTITY_TON": "0.00"}, {"CODE": "HRV", "FLOW": "IMPORT", "YEAR": "2011", "QUANTITY_TON": "0.00"}, {"CODE": "HRV", "FLOW": "IMPORT", "YEAR": "2012", "QUANTITY_TON": "0.00"}, {"CODE": "HRV", "FLOW": "IMPORT", "YEAR": "2013", "QUANTITY_TON": "118.60"}, {"CODE": "HRV", "FLOW": "IMPORT", "YEAR": "2014", "QUANTITY_TON": "356.60"}, {"CODE": "HRV", "FLOW": "IMPORT", "YEAR": "2015", "QUANTITY_TON": "418.90"}, {"CODE": "HRV", "FLOW": "EXPORT", "YEAR": "2010", "QUANTITY_TON": "0.00"}, {"CODE": "HRV", "FLOW": "EXPORT", "YEAR": "2011", "QUANTITY_TON": "0.00"}, {"CODE": "HRV", "FLOW": "EXPORT", "YEAR": "2012", "QUANTITY_TON": "0.00"}, {"CODE": "HRV", "FLOW": "EXPORT", "YEAR": "2013", "QUANTITY_TON": "0.30"}, {"CODE": "HRV", "FLOW": "EXPORT", "YEAR": "2014", "QUANTITY_TON": "0.70"}, {"CODE": "HRV", "FLOW": "EXPORT", "YEAR": "2015", "QUANTITY_TON": "1.30"}, {"CODE": "CYP", "FLOW": "IMPORT", "YEAR": "2010", "QUANTITY_TON": "382.70"}, {"CODE": "CYP", "FLOW": "IMPORT", "YEAR": "2011", "QUANTITY_TON": "87.00"}, {"CODE": "CYP", "FLOW": "IMPORT", "YEAR": "2012", "QUANTITY_TON": "238.10"}, {"CODE": "CYP", "FLOW": "IMPORT", "YEAR": "2013", "QUANTITY_TON": "244.70"}, {"CODE": "CYP", "FLOW": "IMPORT", "YEAR": "2014", "QUANTITY_TON": "351.40"}, {"CODE": "CYP", "FLOW": "IMPORT", "YEAR": "2015", "QUANTITY_TON": "317.40"}, {"CODE": "CYP", "FLOW": "EXPORT", "YEAR": "2010", "QUANTITY_TON": "0.00"}, {"CODE": "CYP", "FLOW": "EXPORT", "YEAR": "2011", "QUANTITY_TON": "0.00"}, {"CODE": "CYP", "FLOW": "EXPORT", "YEAR": "2012", "QUANTITY_TON": "0.00"}, {"CODE": "CYP", "FLOW": "EXPORT", "YEAR": "2013", "QUANTITY_TON": "0.00"}, {"CODE": "CYP", "FLOW": "EXPORT", "YEAR": "2014", "QUANTITY_TON": "1.60"}, {"CODE": "CYP", "FLOW": "EXPORT", "YEAR": "2015", "QUANTITY_TON": "0.00"}]